SPI.v
`timescale 1ps/1ps

module SPIProtocol (
    input  clk,                                         // System Clock
    input  rst,                                         // Asynchronous Reset
    input  [15:0]dat_in,                                // Data Input Vector 
    output spi_mclk,                                    // SPI Clock from Master
    output spi_dat,                                     // SPI bus data
    output spi_ssal,                                    // SPI Slave Select (Active Low)
    output [4:0]bit_count                               // Data bit count
);

reg [15:0] MOSI;                                        // Master-Out Slave-In line
reg [4:0] count;                                        // Control Counter
reg ssal;                                               // Slave Select (Active Low)
reg mclk;                                               // SPI Clock from Master
reg [1:0] state;                                        // SPI State Register

always @ (posedge clk or posedge rst)
if (rst)                                                // Defining the reset state
    begin
        MOSI    <= 16'b0;                               // Clearing the MOSI bus
        count   <= 5'd16;                               // Resetting the bit count to MSB
        ssal    <= 1'b1;                                // Resetting the Slave Select
        mclk    <= 1'b0;                                // Resetting SPI Master Clock 
    end
else
    begin
        case (state)
            0:begin                                     // Initial State
                mclk    <= 1'b0;                        // SPI Master Clock is still zero as no Slave selected
                ssal    <= 1'b1;                        // Slave not selected
                state   <= 1;                           // Going to the next state
              end

            1:begin                                     // Load state
                mclk    <= 1'b0;                        // SPI Master Clock is zero because data is loaded
                ssal    <= 1'b0;                        // Slave Selected
                MOSI    <= dat_in[count-1];           // MOSI Bus is loaded with the data bit
                count   <= count-1;                     // Data bit is shifted
                state   <= 2;                           // Going to the next state
              end
            
            2:begin                                     // Transmission State
                mclk    <= 1'b1;                        // SPI Master Clock is one because data is being transmitted    
                if (count > 0)                          // Checking if all data bits have been exhausted
                    state <= 1;                         // If data bits are remaining, going back to the previous state
                    
                else                                    // If data bits are not remaining then performing the following operations :
                    begin                                   
                        count <= 16;                    // Setting data bit count to MSB
                        state <= 0;                     // Going to state 0
                    end                             
              end

            default:  state <= 0;                       // Default State sets state to 0
        endcase
    end

    assign spi_ssal = ssal;                             // Assigning the port values to the respective reg values
    assign spi_mclk = mclk;
    assign spi_dat  = MOSI;
    assign bit_count = count;

endmodule

SPI_tb.v
`timescale 1ps/1ps
`include "SPI.v"

module SPIProtocol_tb;
    reg clk;                            // Setting input ports
    reg rst;
    reg [15:0] dat_in;

    wire spi_ssal;                      // Setting output ports
    wire spi_mclk;
    wire spi_dat;
    wire [4:0] bit_count;
    
    SPIProtocol uut (                   // Assigning the correct ports 
        .clk(clk),
        .rst(rst),
        .dat_in(dat_in),
        .spi_ssal(spi_ssal),
        .spi_mclk(spi_mclk),
        .spi_dat(spi_dat),
        .bit_count(bit_count)
    );

    initial 
        begin
         $dumpfile("SPI.vcd");           // Creating VCD file to check timing waveforms
         $dumpvars(0,SPIProtocol_tb);    // Setting up the variable environment
        end

    initial                              // Setting up the initial inputs
        begin
           clk      = 0;
           rst      = 1;
           dat_in   = 0;     
        end
    
    always #5 clk = ~clk;                 // Initializing the clock

    initial 
        begin                             // Sending signals from Master to Slave
            #10     rst     = 1'b0;
            #10     dat_in  = 16'hA563;   // Sending a 16 bit data on the SPI Bus
            #355    dat_in  = 16'hFFFF;
            #355    dat_in  = 16'h89DD;       
            #355    dat_in  = 16'h246E;
            #355    rst     = 1'b1; 
            #400    $finish;              // Simulation Endpoint

        end

    initial
        begin
            $monitor(                    // Monitoring the Ports           
                $time,"clk = %b, rst = %b, dat_in = %h, spi_ssal = %b, spi_mclk = %b, spi_dat = %h, bit_count = %d",
                clk, rst, dat_in, spi_ssal, spi_mclk, spi_dat, bit_count
            );   
        end

endmodule

SPI.vcd
$date
	Fri Feb 09 20:33:44 2024
$end
$version
	Icarus Verilog
$end
$timescale
	1ps
$end
$scope module SPIProtocol_tb $end
$var wire 1 ! spi_ssal $end
$var wire 1 " spi_mclk $end
$var wire 1 # spi_dat $end
$var wire 5 $ bit_count [4:0] $end
$var reg 1 % clk $end
$var reg 16 & dat_in [15:0] $end
$var reg 1 ' rst $end
$scope module uut $end
$var wire 5 ( bit_count [4:0] $end
$var wire 1 % clk $end
$var wire 16 ) dat_in [15:0] $end
$var wire 1 ' rst $end
$var wire 1 " spi_mclk $end
$var wire 1 ! spi_ssal $end
$var wire 1 # spi_dat $end
$var reg 16 * MOSI [15:0] $end
$var reg 5 + count [4:0] $end
$var reg 1 , mclk $end
$var reg 1 - ssal $end
$var reg 2 . state [1:0] $end
$upscope $end
$upscope $end
$enddefinitions $end
$comment Show the parameter values. $end
$dumpall
$end
#0
$dumpvars
bx .
1-
0,
b10000 +
b0 *
b0 )
b10000 (
1'
b0 &
0%
b10000 $
0#
0"
1!
$end
#5
1%
#10
0%
0'
#15
b0 .
1%
#20
0%
b1010010101100011 &
b1010010101100011 )
#25
b1 .
1%
#30
0%
#35
1#
b10 .
b1111 $
b1111 (
b1111 +
b1 *
0!
0-
1%
#40
0%
#45
b1 .
1"
1,
1%
#50
0%
#55
0#
b10 .
b1110 $
b1110 (
b1110 +
b0 *
0"
0,
1%
#60
0%
#65
b1 .
1"
1,
1%
#70
0%
#75
1#
b10 .
b1101 $
b1101 (
b1101 +
b1 *
0"
0,
1%
#80
0%
#85
b1 .
1"
1,
1%
#90
0%
#95
0#
b10 .
b1100 $
b1100 (
b1100 +
b0 *
0"
0,
1%
#100
0%
#105
b1 .
1"
1,
1%
#110
0%
#115
b10 .
b1011 $
b1011 (
b1011 +
0"
0,
1%
#120
0%
#125
b1 .
1"
1,
1%
#130
0%
#135
1#
b10 .
b1010 $
b1010 (
b1010 +
b1 *
0"
0,
1%
#140
0%
#145
b1 .
1"
1,
1%
#150
0%
#155
0#
b10 .
b1001 $
b1001 (
b1001 +
b0 *
0"
0,
1%
#160
0%
#165
b1 .
1"
1,
1%
#170
0%
#175
1#
b10 .
b1000 $
b1000 (
b1000 +
b1 *
0"
0,
1%
#180
0%
#185
b1 .
1"
1,
1%
#190
0%
#195
0#
b10 .
b111 $
b111 (
b111 +
b0 *
0"
0,
1%
#200
0%
#205
b1 .
1"
1,
1%
#210
0%
#215
1#
b10 .
b110 $
b110 (
b110 +
b1 *
0"
0,
1%
#220
0%
#225
b1 .
1"
1,
1%
#230
0%
#235
b10 .
b101 $
b101 (
b101 +
0"
0,
1%
#240
0%
#245
b1 .
1"
1,
1%
#250
0%
#255
0#
b10 .
b100 $
b100 (
b100 +
b0 *
0"
0,
1%
#260
0%
#265
b1 .
1"
1,
1%
#270
0%
#275
b10 .
b11 $
b11 (
b11 +
0"
0,
1%
#280
0%
#285
b1 .
1"
1,
1%
#290
0%
#295
b10 .
b10 $
b10 (
b10 +
0"
0,
1%
#300
0%
#305
b1 .
1"
1,
1%
#310
0%
#315
1#
b10 .
b1 $
b1 (
b1 +
b1 *
0"
0,
1%
#320
0%
#325
b1 .
1"
1,
1%
#330
0%
#335
b10 .
b0 $
b0 (
b0 +
0"
0,
1%
#340
0%
#345
b0 .
b10000 $
b10000 (
b10000 +
1"
1,
1%
#350
0%
#355
b1 .
1!
1-
0"
0,
1%
#360
0%
#365
b10 .
b1111 $
b1111 (
b1111 +
0!
0-
1%
#370
0%
#375
b1 .
1"
1,
1%
b1111111111111111 &
b1111111111111111 )
#380
0%
#385
b10 .
b1110 $
b1110 (
b1110 +
0"
0,
1%
#390
0%
#395
b1 .
1"
1,
1%
#400
0%
#405
b10 .
b1101 $
b1101 (
b1101 +
0"
0,
1%
#410
0%
#415
b1 .
1"
1,
1%
#420
0%
#425
b10 .
b1100 $
b1100 (
b1100 +
0"
0,
1%
#430
0%
#435
b1 .
1"
1,
1%
#440
0%
#445
b10 .
b1011 $
b1011 (
b1011 +
0"
0,
1%
#450
0%
#455
b1 .
1"
1,
1%
#460
0%
#465
b10 .
b1010 $
b1010 (
b1010 +
0"
0,
1%
#470
0%
#475
b1 .
1"
1,
1%
#480
0%
#485
b10 .
b1001 $
b1001 (
b1001 +
0"
0,
1%
#490
0%
#495
b1 .
1"
1,
1%
#500
0%
#505
b10 .
b1000 $
b1000 (
b1000 +
0"
0,
1%
#510
0%
#515
b1 .
1"
1,
1%
#520
0%
#525
b10 .
b111 $
b111 (
b111 +
0"
0,
1%
#530
0%
#535
b1 .
1"
1,
1%
#540
0%
#545
b10 .
b110 $
b110 (
b110 +
0"
0,
1%
#550
0%
#555
b1 .
1"
1,
1%
#560
0%
#565
b10 .
b101 $
b101 (
b101 +
0"
0,
1%
#570
0%
#575
b1 .
1"
1,
1%
#580
0%
#585
b10 .
b100 $
b100 (
b100 +
0"
0,
1%
#590
0%
#595
b1 .
1"
1,
1%
#600
0%
#605
b10 .
b11 $
b11 (
b11 +
0"
0,
1%
#610
0%
#615
b1 .
1"
1,
1%
#620
0%
#625
b10 .
b10 $
b10 (
b10 +
0"
0,
1%
#630
0%
#635
b1 .
1"
1,
1%
#640
0%
#645
b10 .
b1 $
b1 (
b1 +
0"
0,
1%
#650
0%
#655
b1 .
1"
1,
1%
#660
0%
#665
b10 .
b0 $
b0 (
b0 +
0"
0,
1%
#670
0%
#675
b0 .
b10000 $
b10000 (
b10000 +
1"
1,
1%
#680
0%
#685
b1 .
1!
1-
0"
0,
1%
#690
0%
#695
b10 .
b1111 $
b1111 (
b1111 +
0!
0-
1%
#700
0%
#705
b1 .
1"
1,
1%
#710
0%
#715
b10 .
b1110 $
b1110 (
b1110 +
0"
0,
1%
#720
0%
#725
b1 .
1"
1,
1%
#730
0%
b1000100111011101 &
b1000100111011101 )
#735
0#
b10 .
b1101 $
b1101 (
b1101 +
b0 *
0"
0,
1%
#740
0%
#745
b1 .
1"
1,
1%
#750
0%
#755
b10 .
b1100 $
b1100 (
b1100 +
0"
0,
1%
#760
0%
#765
b1 .
1"
1,
1%
#770
0%
#775
1#
b10 .
b1011 $
b1011 (
b1011 +
b1 *
0"
0,
1%
#780
0%
#785
b1 .
1"
1,
1%
#790
0%
#795
0#
b10 .
b1010 $
b1010 (
b1010 +
b0 *
0"
0,
1%
#800
0%
#805
b1 .
1"
1,
1%
#810
0%
#815
b10 .
b1001 $
b1001 (
b1001 +
0"
0,
1%
#820
0%
#825
b1 .
1"
1,
1%
#830
0%
#835
1#
b10 .
b1000 $
b1000 (
b1000 +
b1 *
0"
0,
1%
#840
0%
#845
b1 .
1"
1,
1%
#850
0%
#855
b10 .
b111 $
b111 (
b111 +
0"
0,
1%
#860
0%
#865
b1 .
1"
1,
1%
#870
0%
#875
b10 .
b110 $
b110 (
b110 +
0"
0,
1%
#880
0%
#885
b1 .
1"
1,
1%
#890
0%
#895
0#
b10 .
b101 $
b101 (
b101 +
b0 *
0"
0,
1%
#900
0%
#905
b1 .
1"
1,
1%
#910
0%
#915
1#
b10 .
b100 $
b100 (
b100 +
b1 *
0"
0,
1%
#920
0%
#925
b1 .
1"
1,
1%
#930
0%
#935
b10 .
b11 $
b11 (
b11 +
0"
0,
1%
#940
0%
#945
b1 .
1"
1,
1%
#950
0%
#955
b10 .
b10 $
b10 (
b10 +
0"
0,
1%
#960
0%
#965
b1 .
1"
1,
1%
#970
0%
#975
0#
b10 .
b1 $
b1 (
b1 +
b0 *
0"
0,
1%
#980
0%
#985
b1 .
1"
1,
1%
#990
0%
#995
1#
b10 .
b0 $
b0 (
b0 +
b1 *
0"
0,
1%
#1000
0%
#1005
b0 .
b10000 $
b10000 (
b10000 +
1"
1,
1%
#1010
0%
#1015
b1 .
1!
1-
0"
0,
1%
#1020
0%
#1025
b10 .
b1111 $
b1111 (
b1111 +
0!
0-
1%
#1030
0%
#1035
b1 .
1"
1,
1%
#1040
0%
#1045
0#
b10 .
b1110 $
b1110 (
b1110 +
b0 *
0"
0,
1%
#1050
0%
#1055
b1 .
1"
1,
1%
#1060
0%
#1065
b10 .
b1101 $
b1101 (
b1101 +
0"
0,
1%
#1070
0%
#1075
b1 .
1"
1,
1%
#1080
0%
#1085
b10 .
b1100 $
b1100 (
b1100 +
0"
0,
1%
b10010001101110 &
b10010001101110 )
#1090
0%
#1095
b1 .
1"
1,
1%
#1100
0%
#1105
b10 .
b1011 $
b1011 (
b1011 +
0"
0,
1%
#1110
0%
#1115
b1 .
1"
1,
1%
#1120
0%
#1125
1#
b10 .
b1010 $
b1010 (
b1010 +
b1 *
0"
0,
1%
#1130
0%
#1135
b1 .
1"
1,
1%
#1140
0%
#1145
0#
b10 .
b1001 $
b1001 (
b1001 +
b0 *
0"
0,
1%
#1150
0%
#1155
b1 .
1"
1,
1%
#1160
0%
#1165
b10 .
b1000 $
b1000 (
b1000 +
0"
0,
1%
#1170
0%
#1175
b1 .
1"
1,
1%
#1180
0%
#1185
b10 .
b111 $
b111 (
b111 +
0"
0,
1%
#1190
0%
#1195
b1 .
1"
1,
1%
#1200
0%
#1205
1#
b10 .
b110 $
b110 (
b110 +
b1 *
0"
0,
1%
#1210
0%
#1215
b1 .
1"
1,
1%
#1220
0%
#1225
b10 .
b101 $
b101 (
b101 +
0"
0,
1%
#1230
0%
#1235
b1 .
1"
1,
1%
#1240
0%
#1245
0#
b10 .
b100 $
b100 (
b100 +
b0 *
0"
0,
1%
#1250
0%
#1255
b1 .
1"
1,
1%
#1260
0%
#1265
1#
b10 .
b11 $
b11 (
b11 +
b1 *
0"
0,
1%
#1270
0%
#1275
b1 .
1"
1,
1%
#1280
0%
#1285
b10 .
b10 $
b10 (
b10 +
0"
0,
1%
#1290
0%
#1295
b1 .
1"
1,
1%
#1300
0%
#1305
b10 .
b1 $
b1 (
b1 +
0"
0,
1%
#1310
0%
#1315
b1 .
1"
1,
1%
#1320
0%
#1325
0#
b10 .
b0 $
b0 (
b0 +
b0 *
0"
0,
1%
#1330
0%
#1335
b0 .
b10000 $
b10000 (
b10000 +
1"
1,
1%
#1340
0%
#1345
b1 .
1!
1-
0"
0,
1%
#1350
0%
#1355
b10 .
b1111 $
b1111 (
b1111 +
0!
0-
1%
#1360
0%
#1365
b1 .
1"
1,
1%
#1370
0%
#1375
b10 .
b1110 $
b1110 (
b1110 +
0"
0,
1%
#1380
0%
#1385
b1 .
1"
1,
1%
#1390
0%
#1395
1#
b10 .
b1101 $
b1101 (
b1101 +
b1 *
0"
0,
1%
#1400
0%
#1405
b1 .
1"
1,
1%
#1410
0%
#1415
0#
b10 .
b1100 $
b1100 (
b1100 +
b0 *
0"
0,
1%
#1420
0%
#1425
b1 .
1"
1,
1%
#1430
0%
#1435
b10 .
b1011 $
b1011 (
b1011 +
0"
0,
1%
#1440
1!
1-
b10000 $
b10000 (
b10000 +
0%
1'
